dynamicgem/__init__.py
dynamicgem/_version.py
dynamicgem/embedding/TIMERS.py
dynamicgem/embedding/__init__.py
dynamicgem/embedding/ae_static.py
dynamicgem/embedding/dynAE.py
dynamicgem/embedding/dynAERNN.py
dynamicgem/embedding/dynGEM.py
dynamicgem/embedding/dynRNN.py
dynamicgem/embedding/dynamicTriad.py
dynamicgem/embedding/dynamic_graph_embedding.py
dynamicgem/embedding/graphFac_dynamic.py
dynamicgem/embedding/incrementalSVD.py
dynamicgem/embedding/optimalSVD.py
dynamicgem/embedding/rerunSVD.py
dynamicgem/embedding/sdne_dynamic.py
dynamicgem/embedding/static_graph_embedding.py
dynamicgem/evaluation/__init__.py
dynamicgem/evaluation/evaluate_graph_reconstruction.py
dynamicgem/evaluation/evaluate_link_prediction.py
dynamicgem/evaluation/metrics.py
dynamicgem/evaluation/visualize_embedding.py
dynamicgem/experiments/__init__.py
dynamicgem/experiments/exp.py
dynamicgem/experiments/config/__init__.py
dynamicgem/graph_generation/SBM_graph.py
dynamicgem/graph_generation/SBM_node_migration.py
dynamicgem/graph_generation/__init__.py
dynamicgem/graph_generation/createHepTHCollabNet_nx.py
dynamicgem/graph_generation/dynamic_SBM_graph.py
dynamicgem/graph_generation/dynamic_military_call_graph.py
dynamicgem/graph_generation/getAS_nx.py
dynamicgem/graph_generation/motivation.py
dynamicgem/graph_generation/static_military_call_graph.py
dynamicgem/graph_generation/testgraphgen.py
dynamicgem/utils/__init__.py
dynamicgem/utils/dataprep_util.py
dynamicgem/utils/dnn_utils.py
dynamicgem/utils/embed_util.py
dynamicgem/utils/evaluation_util.py
dynamicgem/utils/fig_util.py
dynamicgem/utils/graph_util.py
dynamicgem/utils/plot_util.py
dynamicgem/utils/sdne_utils.py
dynamicgem/utils/timers_utils.py
dynamicgem/utils/ts_utils.py
dynamicgem/utils/dynamictriad_utils/__init__.py
dynamicgem/utils/dynamictriad_utils/gconfig.py
dynamicgem/utils/dynamictriad_utils/gconv.py
dynamicgem/utils/dynamictriad_utils/graphtool_utils.py
dynamicgem/utils/dynamictriad_utils/mygraph_utils.py
dynamicgem-0.0.3.dist-info/LICENSE
dynamicgem-0.0.3.dist-info/METADATA
dynamicgem-0.0.3.dist-info/WHEEL
dynamicgem-0.0.3.dist-info/top_level.txt
dynamicgem-0.0.3.dist-info/RECORD
